setup.cfg
setup.py
jupyterbar/jupyter.py
jupyterbar/jupyterbar.py
jupyterbar.egg-info/PKG-INFO
jupyterbar.egg-info/SOURCES.txt
jupyterbar.egg-info/dependency_links.txt
jupyterbar.egg-info/requires.txt
jupyterbar.egg-info/top_level.txt