Metadata-Version: 1.1
Name: jupyterbar
Version: 0.1
Summary: A little statusbar for http://jupyter.org (http://ipython.org/) on OS X written in Python.
Home-page: https://github.com/C-Codes/jupyterbar
Author: Christoph Russ
Author-email: chruss@gmx.de
License: MIT
Download-URL: https://github.com/C-Codes/jupyterbar/tarball/v0.1
Platform: UNKNOWN
Classifier: Development Status :: 3 - Alpha
Classifier: Environment :: MacOS X
Classifier: Framework :: IPython
Classifier: License :: OSI Approved :: MIT License
Classifier: Natural Language :: English
Classifier: Operating System :: MacOS :: MacOS X
Classifier: Programming Language :: Python :: 2
Classifier: Programming Language :: Python :: 3
